fixr/_xrif.py
fixr/__init__.py
fixr/libxrif.dylib
fixr-0.2.1.dist-info/RECORD
fixr-0.2.1.dist-info/WHEEL
fixr-0.2.1.dist-info/top_level.txt
fixr-0.2.1.dist-info/METADATA
fixr-0.2.1.dist-info/licenses/LICENSE
