Metadata-Version: 2.4
Name: fixr
Version: 0.2.1
Summary: Python bindings to xrif, the extreme reordered image format
Requires-Python: >=3.10
License-File: LICENSE
Requires-Dist: numpy>=2
Dynamic: license-file
